{"top5scorers":[{"scorer":"Jeton Bytyqi","goals":7,"team":"FC Egerkingen"},{"scorer":"Baran Ildeniz","goals":6,"team":"Kurdischer FC Solothurn"},{"scorer":"Christoph Jenni","goals":5,"team":"FC Selzach"},{"scorer":"Murat Kaplan","goals":5,"team":"FC Winznau"},{"scorer":"Kevin Von Rohr","goals":3,"team":"FC Hägendorf"},{"scorer":"Nirosan Mahendran","goals":2,"team":"FC Bettlach"},{"scorer":"Lulzim Krasniqi","goals":2,"team":"FC Egerkingen"},{"scorer":"Nico Guldimann","goals":2,"team":"FC Winznau"},{"scorer":"Cedric Mägli","goals":1,"team":"FC Niederbipp"},{"scorer":"csc","goals":1,"team":"FC Deitingen"},{"scorer":"Matthias Schmid","goals":1,"team":"FC Attiswil"},{"scorer":"Maximian von Burg","goals":1,"team":"FC Bettlach"},{"scorer":"Thomas Caflisch","goals":1,"team":"FC Bettlach"},{"scorer":"André Cristiano Ribeiro","goals":1,"team":"FC Niederbipp"},{"scorer":"Stefan Berner","goals":1,"team":"FC Attiswil"},{"scorer":"Hrvoje Vrljic","goals":1,"team":"FC Hägendorf"},{"scorer":"Nicolas Roth","goals":1,"team":"FC Olten"},{"scorer":"Fabio Strähl","goals":1,"team":"FC Deitingen"},{"scorer":"Ahmet Poyraz","goals":1,"team":"FC Hägendorf"},{"scorer":"Raphael Nydegger","goals":1,"team":"FC Deitingen"}]}