{"top5scorers":[{"scorer":"Baran Ildeniz","goals":18,"team":"Kurdischer FC Solothurn"},{"scorer":"Mario Gobeli","goals":17,"team":"FC Attiswil"},{"scorer":"Marc Seuret","goals":14,"team":"FC Bettlach"},{"scorer":"Jeton Bytyqi","goals":9,"team":"FC Egerkingen"},{"scorer":"Kendal Kaya","goals":9,"team":"Kurdischer FC Solothurn"},{"scorer":"Sandro Brunner","goals":9,"team":"FC Oensingen a"},{"scorer":"David Rota","goals":9,"team":"FC Wangen a/A"},{"scorer":"Christoph Jenni","goals":8,"team":"FC Selzach"},{"scorer":"Bruno Nellen","goals":7,"team":"FC Selzach"},{"scorer":"Luca Romano","goals":7,"team":"FC Selzach"},{"scorer":"Marcel Haudenschild","goals":7,"team":"FC Rüttenen"},{"scorer":"Fabian Messerli","goals":6,"team":"FC Niederbipp"},{"scorer":"Denis Mehmedovic","goals":6,"team":"FC Olten"},{"scorer":"Jihed Hamami","goals":5,"team":"FC Olten"},{"scorer":"Atdhe Krasniqi","goals":5,"team":"FC Egerkingen"},{"scorer":"Nirosan Mahendran","goals":5,"team":"FC Bettlach"},{"scorer":"Lenny Poffa","goals":5,"team":"Niederamt Selection"},{"scorer":"Agon Zeka","goals":5,"team":"FC Oensingen a"},{"scorer":"Murat Kaplan","goals":5,"team":"FC Winznau"},{"scorer":"Daniel Flück","goals":5,"team":"FC Hägendorf"}]}