{"teams":[{"rank":1,"rankwas":1,"team":"FC Schwarz-Weiss a","goalsfor":17,"goalsagainst":1,"won":1,"tied":0,"lost":0,"fairplay":0,"points":3,"group":5,"region":"fvnws","evolution":[1]},{"rank":2,"rankwas":2,"team":"BCO Alemannia Basel a","goalsfor":3,"goalsagainst":1,"won":1,"tied":0,"lost":0,"fairplay":0,"points":3,"group":5,"region":"fvnws","evolution":[2]},{"rank":3,"rankwas":3,"team":"FC Polizei Basel a","goalsfor":6,"goalsagainst":3,"won":1,"tied":0,"lost":0,"fairplay":1,"points":3,"group":5,"region":"fvnws","evolution":[3]},{"rank":4,"rankwas":4,"team":"FF Brüglingen Basel","goalsfor":1,"goalsagainst":1,"won":0,"tied":1,"lost":0,"fairplay":0,"points":1,"group":5,"region":"fvnws","evolution":[4]},{"rank":5,"rankwas":5,"team":"AS Timau Basel","goalsfor":3,"goalsagainst":3,"won":0,"tied":1,"lost":0,"fairplay":1,"points":1,"group":5,"region":"fvnws","evolution":[5]},{"rank":5,"rankwas":5,"team":"SC Münchenstein","goalsfor":3,"goalsagainst":3,"won":0,"tied":1,"lost":0,"fairplay":1,"points":1,"group":5,"region":"fvnws","evolution":[5]},{"rank":7,"rankwas":7,"team":"FC Bosna Basel","goalsfor":1,"goalsagainst":1,"won":0,"tied":1,"lost":0,"fairplay":4,"points":1,"group":5,"region":"fvnws","evolution":[7]},{"rank":8,"rankwas":8,"team":"NK Alkar","goalsfor":0,"goalsagainst":0,"won":0,"tied":0,"lost":0,"fairplay":0,"points":0,"group":5,"region":"fvnws","evolution":[8]},{"rank":9,"rankwas":9,"team":"SC Basel Nord b","goalsfor":1,"goalsagainst":3,"won":0,"tied":0,"lost":1,"fairplay":0,"points":0,"group":5,"region":"fvnws","evolution":[9]},{"rank":10,"rankwas":10,"team":"FC Amicitia Riehen","goalsfor":3,"goalsagainst":6,"won":0,"tied":0,"lost":1,"fairplay":0,"points":0,"group":5,"region":"fvnws","evolution":[10]},{"rank":11,"rankwas":11,"team":"FC Allschwil","goalsfor":1,"goalsagainst":17,"won":0,"tied":0,"lost":1,"fairplay":1,"points":0,"group":5,"region":"fvnws","evolution":[11]}]}