{"rankings":[{"groupNumber":1,"scorers":[{"scorer":"Fabian Frick","goals":13,"team":"GS Italgrenchen"},{"scorer":"Philipp Breu","goals":10,"team":"FC Gerlafingen"},{"scorer":"Bozo Krizanovic","goals":10,"team":"HNK Croatia"},{"scorer":"Lukas Hauri","goals":9,"team":"FC Kestenholz"},{"scorer":"Sacha Kissling","goals":9,"team":"FC Kestenholz"},{"scorer":"Tobias Stalder","goals":9,"team":"FC Deitingen"},{"scorer":"Benjamin Walker","goals":8,"team":"FC Bettlach"},{"scorer":"Damian Thomi","goals":8,"team":"FC Subingen"},{"scorer":"Marco Maric","goals":8,"team":"HNK Croatia"},{"scorer":"Boris Flury","goals":7,"team":"FC Selzach"},{"scorer":"David Flury","goals":7,"team":"FC Deitingen"},{"scorer":"Jetlir Bytyqi","goals":6,"team":"FC Gerlafingen"},{"scorer":"Florian Haas","goals":6,"team":"FC Wangen a/A"},{"scorer":"Simon Jost","goals":6,"team":"HSV Halten"},{"scorer":"Ibrahim Cil","goals":6,"team":"FC Post Solothurn"},{"scorer":"Pascal Winistörfer","goals":6,"team":"FC Subingen"},{"scorer":"Marinko Zizak","goals":6,"team":"HNK Croatia"},{"scorer":"Dominic De Chiara","goals":6,"team":"FC Winznau"},{"scorer":"Manuel Fernando Alves","goals":5,"team":"FC Niederbipp"},{"scorer":"Manuel Reber","goals":5,"team":"FC Riedholz"},{"scorer":"Joel Marc Bessire","goals":5,"team":"HSV Halten"},{"scorer":"Xaver Meyer","goals":5,"team":"FC Olten"},{"scorer":"Aron Heynen","goals":5,"team":"FC Rüttenen"},{"scorer":"Valon Kadrija","goals":4,"team":"FC Zuchwil"},{"scorer":"Beytullah Özdemir","goals":4,"team":"FC Gerlafingen"},{"scorer":"Samuel Piazza","goals":4,"team":"FC Post Solothurn"},{"scorer":"Raphael Kissling","goals":4,"team":"FC Wolfwil"},{"scorer":"Christian Rudolf von Rohr","goals":4,"team":"FC Riedholz"},{"scorer":"Saber Raowfy","goals":4,"team":"FC Klus-Balsthal"},{"scorer":"Simon Nobs","goals":4,"team":"FC Rüttenen"},{"scorer":"Philipp Flück","goals":4,"team":"FC Hägendorf"},{"scorer":"Erdal Yildizli","goals":4,"team":"Türkischer SC Solothurn"},{"scorer":"Orhan Zulfi","goals":4,"team":"FC Selzach"},{"scorer":"Burak Yildizli","goals":4,"team":"Türkischer SC Solothurn"},{"scorer":"Daniel Ernst","goals":4,"team":"HSV Halten"},{"scorer":"Astrit Tuqi","goals":4,"team":"FC Kestenholz"},{"scorer":"Oguzhan Tonus","goals":4,"team":"FC Egerkingen"},{"scorer":"Stefan Nikodijevic","goals":4,"team":"FC Olten"},{"scorer":"Yannik Aebischer","goals":4,"team":"FC Leuzigen"},{"scorer":"Tayfun Demirci","goals":3,"team":"FC Post Solothurn"},{"scorer":"Nicolas Born","goals":3,"team":"FC Niederbipp"},{"scorer":"Luigi Abbagnale","goals":3,"team":"FC Egerkingen"},{"scorer":"Misin Shala","goals":3,"team":"FC Niederbipp"},{"scorer":"Patrick Murer","goals":3,"team":"FC Deitingen"},{"scorer":"Rit Slishani","goals":3,"team":"FC Olten"},{"scorer":"Batuhan Baladin","goals":3,"team":"FC Zuchwil"},{"scorer":"Jan Zimmerli","goals":3,"team":"FC Hägendorf"},{"scorer":"Jonas Zuber","goals":3,"team":"FC Deitingen"},{"scorer":"Kosta Milosevic","goals":3,"team":"FC Klus-Balsthal"},{"scorer":"Giuseppe Tiralongo","goals":3,"team":"GS Italgrenchen"},{"scorer":"Fabian Pfister","goals":3,"team":"FC Wangen a/A"},{"scorer":"Mario Belakusic","goals":3,"team":"FC Zuchwil"},{"scorer":"Ali Halimi","goals":3,"team":"FC Olten"},{"scorer":"Oliver Andrijasevic","goals":3,"team":"HNK Croatia"},{"scorer":"Angelo Rubino","goals":3,"team":"FC Olten"},{"scorer":"Davide Lipari","goals":3,"team":"FC Hägendorf"},{"scorer":"Gianfranco Vinci","goals":3,"team":"FC Olten"},{"scorer":"Volkan Turhan","goals":3,"team":"FC Gerlafingen"},{"scorer":"Kevin Zingg","goals":3,"team":"FC Bettlach"},{"scorer":"Silvan Rudolf von Rohr","goals":3,"team":"FC Riedholz"},{"scorer":"Michael Jeggli","goals":3,"team":"FC Wolfwil"},{"scorer":"Raphael Aebischer","goals":3,"team":"FC Leuzigen"},{"scorer":"Cheick Youssouf Konate","goals":3,"team":"FC Klus-Balsthal"},{"scorer":"Ahmet Poyraz","goals":3,"team":"FC Hägendorf"},{"scorer":"Edin Pepik","goals":2,"team":"FC Hägendorf"},{"scorer":"Deniz Mendi","goals":2,"team":"FC Klus-Balsthal"},{"scorer":"Robin Kaufmann","goals":2,"team":"FC Riedholz"},{"scorer":"Adrian Wiemann","goals":2,"team":"FC Kestenholz"},{"scorer":"Mingiedi Kiala","goals":2,"team":"FC Niederbipp"},{"scorer":"Dario Schneider","goals":2,"team":"FC Gerlafingen"},{"scorer":"Driton Hasani","goals":2,"team":"FC Hägendorf"},{"scorer":"Ivan Krivic","goals":2,"team":"HNK Croatia"},{"scorer":"Alessandro Mirarchi","goals":2,"team":"FC Olten"},{"scorer":"Silvio Cataldi","goals":2,"team":"GS Italgrenchen"},{"scorer":"Mike Uebelhart","goals":2,"team":"FC Wolfwil"},{"scorer":"Yanick Kofmehl","goals":2,"team":"FC Subingen"},{"scorer":"Tim Kissling","goals":2,"team":"FC Kestenholz"},{"scorer":"Gianluigi De Pascali","goals":2,"team":"FC Winznau"},{"scorer":"Tobias Tschumi","goals":2,"team":"FC Riedholz"},{"scorer":"Samuel Bur","goals":2,"team":"FC Bettlach"},{"scorer":"Mihael Petrovic","goals":2,"team":"HNK Croatia"},{"scorer":"Adis Gromilic","goals":2,"team":"GS Italgrenchen"},{"scorer":"Andreas Trösch","goals":2,"team":"FC Wangen a/A"},{"scorer":"André Zimmermann","goals":2,"team":"Türkischer SC Solothurn"},{"scorer":"Iwan Schläfli","goals":2,"team":"HSV Halten"},{"scorer":"Marco Scherrer","goals":2,"team":"FC Klus-Balsthal"},{"scorer":"Özkan Sogukcelik","goals":2,"team":"Türkischer SC Solothurn"},{"scorer":"Sascha Hess","goals":2,"team":"FC Selzach"},{"scorer":"Dominic Müller","goals":2,"team":"FC Rüttenen"},{"scorer":"Jonas Stuber","goals":2,"team":"FC Leuzigen"},{"scorer":"Jari Eggenschwiler","goals":2,"team":"GS Italgrenchen"},{"scorer":"Raphael Stalder","goals":2,"team":"FC Deitingen"},{"scorer":"Moritz Frey","goals":2,"team":"FC Rüttenen"},{"scorer":"Muhamed Trumic","goals":2,"team":"FC Niederbipp"},{"scorer":"Michael Winter","goals":2,"team":"HSV Halten"},{"scorer":"Sebastian Meister","goals":2,"team":"FC Rüttenen"},{"scorer":"Fabian Grütter","goals":2,"team":"FC Riedholz"},{"scorer":"Mike Keller","goals":2,"team":"FC Winznau"},{"scorer":"Francis Bossman","goals":2,"team":"FC Niederbipp"},{"scorer":"Silas Zurschmiede","goals":2,"team":"FC Leuzigen"},{"scorer":"Ronny Joss","goals":2,"team":"FC Selzach"},{"scorer":"Tobias Ross","goals":2,"team":"HSV Halten"},{"scorer":"Josip Aracic","goals":2,"team":"HNK Croatia"},{"scorer":"Michael Schneitter","goals":2,"team":"FC Riedholz"},{"scorer":"Simon Meier","goals":2,"team":"FC Kestenholz"},{"scorer":"Nils Schneider","goals":2,"team":"FC Kestenholz"},{"scorer":"Davide Marcucci","goals":2,"team":"FC Gerlafingen"},{"scorer":"Mariano Schneeberger","goals":2,"team":"FC Niederbipp"},{"scorer":"Eric Kohler","goals":2,"team":"FC Bettlach"},{"scorer":"Kerim Balikcioglu","goals":2,"team":"Türkischer SC Solothurn"},{"scorer":"Jonas Knörr","goals":2,"team":"FC Selzach"},{"scorer":"Haydar Gökgül","goals":2,"team":"Türkischer SC Solothurn"},{"scorer":"Gabriel Stampfli","goals":2,"team":"FC Deitingen"},{"scorer":"Joël Grolimund","goals":2,"team":"FC Winznau"},{"scorer":"Mathias Studer","goals":2,"team":"FC Subingen"},{"scorer":"Artak Papojan","goals":2,"team":"FC Klus-Balsthal"},{"scorer":"Marc Taschler","goals":2,"team":"FC Kestenholz"},{"scorer":"André Schenk","goals":2,"team":"FC Wolfwil"},{"scorer":"Kevin Sriwong","goals":2,"team":"FC Bettlach"},{"scorer":"Yves Wälti","goals":2,"team":"FC Wangen a/A"},{"scorer":"Robin Flück","goals":2,"team":"FC Hägendorf"}]}],"lastUpdate":"27/10/2017 @ 13h00","lastUpdateForSiteMap":"2017-10-27"}