{"teams":[{"rank":1,"rankwas":1,"team":"FC Corminboeuf I","goalsfor":0,"goalsagainst":0,"won":0,"tied":0,"lost":0,"fairplay":0,"points":0,"group":2,"region":"aff","evolution":[1,1]},{"rank":1,"rankwas":1,"team":"FC Courgevaux I","goalsfor":0,"goalsagainst":0,"won":0,"tied":0,"lost":0,"fairplay":0,"points":0,"group":2,"region":"aff","evolution":[1,1]},{"rank":1,"rankwas":1,"team":"FC Cressier I","goalsfor":0,"goalsagainst":0,"won":0,"tied":0,"lost":0,"fairplay":0,"points":0,"group":2,"region":"aff","evolution":[1,1]},{"rank":1,"rankwas":1,"team":"SC Düdingen II","goalsfor":0,"goalsagainst":0,"won":0,"tied":0,"lost":0,"fairplay":0,"points":0,"group":2,"region":"aff","evolution":[1,1]},{"rank":1,"rankwas":1,"team":"FC Gurmels I","goalsfor":0,"goalsagainst":0,"won":0,"tied":0,"lost":0,"fairplay":0,"points":0,"group":2,"region":"aff","evolution":[1,1]},{"rank":1,"rankwas":1,"team":"FC Kerzers II","goalsfor":0,"goalsagainst":0,"won":0,"tied":0,"lost":0,"fairplay":0,"points":0,"group":2,"region":"aff","evolution":[1,1]},{"rank":1,"rankwas":1,"team":"FC Tafers I","goalsfor":0,"goalsagainst":0,"won":0,"tied":0,"lost":0,"fairplay":0,"points":0,"group":2,"region":"aff","evolution":[1,1]},{"rank":1,"rankwas":1,"team":"FC Schmitten I","goalsfor":0,"goalsagainst":0,"won":0,"tied":0,"lost":0,"fairplay":0,"points":0,"group":2,"region":"aff","evolution":[1,1]},{"rank":1,"rankwas":1,"team":"FC Giffers-Tentlingen I","goalsfor":0,"goalsagainst":0,"won":0,"tied":0,"lost":0,"fairplay":0,"points":0,"group":2,"region":"aff","evolution":[1,1]},{"rank":1,"rankwas":1,"team":"FC Alterswil I","goalsfor":0,"goalsagainst":0,"won":0,"tied":0,"lost":0,"fairplay":0,"points":0,"group":2,"region":"aff","evolution":[1,1]},{"rank":1,"rankwas":1,"team":"FC Seisa 08 I","goalsfor":0,"goalsagainst":0,"won":0,"tied":0,"lost":0,"fairplay":0,"points":0,"group":2,"region":"aff","evolution":[1,1]},{"rank":1,"rankwas":1,"team":"FC Plasselb I","goalsfor":0,"goalsagainst":0,"won":0,"tied":0,"lost":0,"fairplay":0,"points":0,"group":2,"region":"aff","evolution":[1,1]}]}