{"teams":[{"rank":1,"rankwas":1,"team":"FC Sarine-Ouest I","goalsfor":43,"goalsagainst":16,"won":13,"tied":3,"lost":3,"fairplay":32,"points":42,"group":1,"region":"aff","evolution":[6,8,6,8,6,3,2,2,2,1,3,2,1,1,1,1,1]},{"rank":2,"rankwas":2,"team":"FC Piamont I","goalsfor":50,"goalsagainst":28,"won":11,"tied":4,"lost":4,"fairplay":46,"points":37,"group":1,"region":"aff","evolution":[4,4,2,4,7,5,3,3,4,3,2,1,2,2,4,4,2]},{"rank":3,"rankwas":3,"team":"FC Schoenberg I","goalsfor":58,"goalsagainst":29,"won":10,"tied":6,"lost":3,"fairplay":54,"points":36,"group":1,"region":"aff","evolution":[11,7,8,6,8,6,7,5,5,5,4,6,5,3,2,2,3]},{"rank":4,"rankwas":4,"team":"FC Estavayer-le-Gibloux I","goalsfor":40,"goalsagainst":27,"won":10,"tied":5,"lost":4,"fairplay":31,"points":35,"group":1,"region":"aff","evolution":[1,2,4,7,5,8,8,8,6,6,6,4,4,4,3,3,4]},{"rank":5,"rankwas":5,"team":"FC La Roche/Pont-la-Ville I","goalsfor":41,"goalsagainst":24,"won":10,"tied":5,"lost":4,"fairplay":37,"points":35,"group":1,"region":"aff","evolution":[2,5,7,5,2,1,1,1,1,2,1,3,3,5,5,5,5]},{"rank":6,"rankwas":6,"team":"FC Villars-sur-Glâne I","goalsfor":57,"goalsagainst":38,"won":10,"tied":1,"lost":8,"fairplay":38,"points":31,"group":1,"region":"aff","evolution":[3,1,3,1,3,2,5,7,9,9,9,8,7,7,7,7,6]},{"rank":7,"rankwas":7,"team":"FC Siviriez I","goalsfor":42,"goalsagainst":25,"won":9,"tied":2,"lost":8,"fairplay":40,"points":29,"group":1,"region":"aff","evolution":[9,6,5,2,4,7,6,4,3,4,5,5,6,6,6,6,7]},{"rank":8,"rankwas":8,"team":"FC Châtel-St-Denis I","goalsfor":38,"goalsagainst":33,"won":7,"tied":5,"lost":7,"fairplay":84,"points":26,"group":1,"region":"aff","evolution":[7,9,11,11,9,9,9,9,8,7,8,9,9,9,9,9,8]},{"rank":9,"rankwas":9,"team":"FC Central FR I","goalsfor":35,"goalsagainst":40,"won":7,"tied":3,"lost":9,"fairplay":56,"points":24,"group":1,"region":"aff","evolution":[5,3,1,3,1,4,4,6,7,8,7,7,8,8,8,8,9]},{"rank":10,"rankwas":10,"team":"FC Bas-Gibloux I","goalsfor":24,"goalsagainst":40,"won":4,"tied":5,"lost":10,"fairplay":47,"points":17,"group":1,"region":"aff","evolution":[8,10,9,9,10,10,10,11,11,11,10,10,10,10,10,10,10]},{"rank":11,"rankwas":11,"team":"FC Fribourg II","goalsfor":20,"goalsagainst":55,"won":3,"tied":1,"lost":15,"fairplay":45,"points":10,"group":1,"region":"aff","evolution":[10,11,10,10,11,11,11,10,10,10,11,11,11,11,11,11,11]},{"rank":12,"rankwas":12,"team":"FC Charmey I","goalsfor":11,"goalsagainst":104,"won":0,"tied":0,"lost":19,"fairplay":43,"points":0,"group":1,"region":"aff","evolution":[12,12,12,12,12,12,12,12,12,12,12,12,12,12,12,12,12]}]}