{"teams":[{"rank":1,"rankwas":1,"team":"FC Vuisternens/Mézières II","goalsfor":0,"goalsagainst":0,"won":0,"tied":0,"lost":0,"fairplay":0,"points":0,"group":2,"region":"aff"},{"rank":1,"rankwas":1,"team":"FC Vuadens II","goalsfor":0,"goalsagainst":0,"won":0,"tied":0,"lost":0,"fairplay":0,"points":0,"group":1,"region":"aff"},{"rank":1,"rankwas":1,"team":"FC Treyvaux","goalsfor":0,"goalsagainst":0,"won":0,"tied":0,"lost":0,"fairplay":0,"points":0,"group":1,"region":"aff"},{"rank":1,"rankwas":1,"team":"FC Broc II","goalsfor":0,"goalsagainst":0,"won":0,"tied":0,"lost":0,"fairplay":0,"points":0,"group":1,"region":"aff"},{"rank":1,"rankwas":1,"team":"FC Châtel-St-Denis II","goalsfor":0,"goalsagainst":0,"won":0,"tied":0,"lost":0,"fairplay":0,"points":0,"group":1,"region":"aff"},{"rank":1,"rankwas":1,"team":"FC Riaz II","goalsfor":0,"goalsagainst":0,"won":0,"tied":0,"lost":0,"fairplay":0,"points":0,"group":1,"region":"aff"},{"rank":1,"rankwas":1,"team":"FC Charmey II","goalsfor":0,"goalsagainst":0,"won":0,"tied":0,"lost":0,"fairplay":0,"points":0,"group":1,"region":"aff"},{"rank":1,"rankwas":1,"team":"FC Château-d'Oex","goalsfor":0,"goalsagainst":0,"won":0,"tied":0,"lost":0,"fairplay":0,"points":0,"group":1,"region":"aff"},{"rank":1,"rankwas":1,"team":"FC Bulle II","goalsfor":0,"goalsagainst":0,"won":0,"tied":0,"lost":0,"fairplay":0,"points":0,"group":1,"region":"aff"},{"rank":1,"rankwas":1,"team":"FC La Sionge II","goalsfor":0,"goalsagainst":0,"won":0,"tied":0,"lost":0,"fairplay":0,"points":0,"group":1,"region":"aff"},{"rank":1,"rankwas":1,"team":"Continental Club Corbières II","goalsfor":0,"goalsagainst":0,"won":0,"tied":0,"lost":0,"fairplay":0,"points":0,"group":1,"region":"aff"},{"rank":1,"rankwas":1,"team":"FC Gruyère-Lac II","goalsfor":0,"goalsagainst":0,"won":0,"tied":0,"lost":0,"fairplay":0,"points":0,"group":2,"region":"aff"},{"rank":1,"rankwas":1,"team":"FC Farvagny/Ogoz III","goalsfor":0,"goalsagainst":0,"won":0,"tied":0,"lost":0,"fairplay":0,"points":0,"group":2,"region":"aff"},{"rank":1,"rankwas":1,"team":"FC Léchelles II","goalsfor":0,"goalsagainst":0,"won":0,"tied":0,"lost":0,"fairplay":0,"points":0,"group":4,"region":"aff"},{"rank":1,"rankwas":1,"team":"FC Ressudens II","goalsfor":0,"goalsagainst":0,"won":0,"tied":0,"lost":0,"fairplay":0,"points":0,"group":4,"region":"aff"},{"rank":1,"rankwas":1,"team":"FC Villarepos","goalsfor":0,"goalsagainst":0,"won":0,"tied":0,"lost":0,"fairplay":0,"points":0,"group":4,"region":"aff"},{"rank":1,"rankwas":1,"team":"FC Nuvilly","goalsfor":0,"goalsagainst":0,"won":0,"tied":0,"lost":0,"fairplay":0,"points":0,"group":4,"region":"aff"},{"rank":1,"rankwas":1,"team":"U.S.C.V.","goalsfor":0,"goalsagainst":0,"won":0,"tied":0,"lost":0,"fairplay":0,"points":0,"group":4,"region":"aff"},{"rank":1,"rankwas":1,"team":"FC Piamont II","goalsfor":0,"goalsagainst":0,"won":0,"tied":0,"lost":0,"fairplay":0,"points":0,"group":4,"region":"aff"},{"rank":1,"rankwas":1,"team":"FC Montagny II","goalsfor":0,"goalsagainst":0,"won":0,"tied":0,"lost":0,"fairplay":0,"points":0,"group":4,"region":"aff"},{"rank":1,"rankwas":1,"team":"FC Tafers III","goalsfor":1,"goalsagainst":0,"won":1,"tied":0,"lost":0,"fairplay":0,"points":3,"group":5,"region":"aff"},{"rank":1,"rankwas":1,"team":"FC Massonnens","goalsfor":0,"goalsagainst":0,"won":0,"tied":0,"lost":0,"fairplay":0,"points":0,"group":2,"region":"aff"},{"rank":1,"rankwas":1,"team":"FC Châtonnaye/Middes II","goalsfor":0,"goalsagainst":0,"won":0,"tied":0,"lost":0,"fairplay":0,"points":0,"group":2,"region":"aff"},{"rank":1,"rankwas":1,"team":"FC Bas-Gibloux II","goalsfor":0,"goalsagainst":0,"won":0,"tied":0,"lost":0,"fairplay":0,"points":0,"group":2,"region":"aff"},{"rank":1,"rankwas":1,"team":"FC Rue","goalsfor":0,"goalsagainst":0,"won":0,"tied":0,"lost":0,"fairplay":0,"points":0,"group":2,"region":"aff"},{"rank":1,"rankwas":1,"team":"FC Siviriez II","goalsfor":0,"goalsagainst":0,"won":0,"tied":0,"lost":0,"fairplay":0,"points":0,"group":2,"region":"aff"},{"rank":1,"rankwas":1,"team":"FC Sarine-Ouest III","goalsfor":0,"goalsagainst":0,"won":0,"tied":0,"lost":0,"fairplay":0,"points":0,"group":2,"region":"aff"},{"rank":1,"rankwas":2,"team":"FC Courgevaux II","goalsfor":0,"goalsagainst":0,"won":0,"tied":0,"lost":0,"fairplay":0,"points":0,"group":5,"region":"aff"},{"rank":1,"rankwas":1,"team":"FC Estavayer-le-Gibloux II","goalsfor":0,"goalsagainst":0,"won":0,"tied":0,"lost":0,"fairplay":0,"points":0,"group":2,"region":"aff"},{"rank":1,"rankwas":1,"team":"FC Chénens/Autigny","goalsfor":0,"goalsagainst":0,"won":0,"tied":0,"lost":0,"fairplay":0,"points":0,"group":2,"region":"aff"},{"rank":1,"rankwas":1,"team":"FC Villaz/Villarimboud II","goalsfor":0,"goalsagainst":0,"won":0,"tied":0,"lost":0,"fairplay":0,"points":0,"group":2,"region":"aff"},{"rank":1,"rankwas":1,"team":"FC Cugy/Montet II","goalsfor":0,"goalsagainst":0,"won":0,"tied":0,"lost":0,"fairplay":0,"points":0,"group":4,"region":"aff"},{"rank":1,"rankwas":1,"team":"FC Remaufens","goalsfor":0,"goalsagainst":0,"won":0,"tied":0,"lost":0,"fairplay":0,"points":0,"group":1,"region":"aff"},{"rank":1,"rankwas":1,"team":"FC Petite-Glâne","goalsfor":0,"goalsagainst":0,"won":0,"tied":0,"lost":0,"fairplay":0,"points":0,"group":4,"region":"aff"},{"rank":1,"rankwas":1,"team":"FC Dompierre ","goalsfor":0,"goalsagainst":0,"won":0,"tied":0,"lost":0,"fairplay":0,"points":0,"group":4,"region":"aff"},{"rank":1,"rankwas":1,"team":"FC Montbrelloz II","goalsfor":0,"goalsagainst":0,"won":0,"tied":0,"lost":0,"fairplay":0,"points":0,"group":4,"region":"aff"},{"rank":1,"rankwas":1,"team":"US Cheyres-Châbles-Font II","goalsfor":0,"goalsagainst":0,"won":0,"tied":0,"lost":0,"fairplay":0,"points":0,"group":4,"region":"aff"},{"rank":2,"rankwas":1,"team":"FC Wünnewil-Flamatt IIb","goalsfor":0,"goalsagainst":0,"won":0,"tied":0,"lost":0,"fairplay":0,"points":0,"group":5,"region":"aff"},{"rank":2,"rankwas":1,"team":"FC Grolley","goalsfor":0,"goalsagainst":0,"won":0,"tied":0,"lost":0,"fairplay":0,"points":0,"group":3,"region":"aff"},{"rank":2,"rankwas":1,"team":"FC Gurmels II","goalsfor":0,"goalsagainst":0,"won":0,"tied":0,"lost":0,"fairplay":0,"points":0,"group":3,"region":"aff"},{"rank":2,"rankwas":1,"team":"Team Haut-Lac (5054) III","goalsfor":0,"goalsagainst":0,"won":0,"tied":0,"lost":0,"fairplay":0,"points":0,"group":3,"region":"aff"},{"rank":2,"rankwas":1,"team":"FC Etoile-Sport II","goalsfor":0,"goalsagainst":0,"won":0,"tied":0,"lost":0,"fairplay":0,"points":0,"group":3,"region":"aff"},{"rank":2,"rankwas":1,"team":"FC Cudrefin II","goalsfor":0,"goalsagainst":0,"won":0,"tied":0,"lost":0,"fairplay":0,"points":0,"group":3,"region":"aff"},{"rank":2,"rankwas":1,"team":"FC Vully-Sport II","goalsfor":0,"goalsagainst":0,"won":0,"tied":0,"lost":0,"fairplay":0,"points":0,"group":3,"region":"aff"},{"rank":2,"rankwas":1,"team":"FC Granges-Paccot II","goalsfor":0,"goalsagainst":0,"won":0,"tied":0,"lost":0,"fairplay":0,"points":0,"group":5,"region":"aff"},{"rank":2,"rankwas":1,"team":"FC Seisa 08 III","goalsfor":0,"goalsagainst":0,"won":0,"tied":0,"lost":0,"fairplay":0,"points":0,"group":5,"region":"aff"},{"rank":2,"rankwas":1,"team":"FC Wünnewil-Flamatt IIa","goalsfor":0,"goalsagainst":0,"won":0,"tied":0,"lost":0,"fairplay":0,"points":0,"group":3,"region":"aff"},{"rank":2,"rankwas":1,"team":"FC Givisiez II","goalsfor":0,"goalsagainst":0,"won":0,"tied":0,"lost":0,"fairplay":0,"points":0,"group":3,"region":"aff"},{"rank":2,"rankwas":1,"team":"FC Fribourg III","goalsfor":0,"goalsagainst":0,"won":0,"tied":0,"lost":0,"fairplay":0,"points":0,"group":3,"region":"aff"},{"rank":2,"rankwas":1,"team":"FC Plasselb II","goalsfor":0,"goalsagainst":0,"won":0,"tied":0,"lost":0,"fairplay":0,"points":0,"group":5,"region":"aff"},{"rank":2,"rankwas":1,"team":"FC Schmitten II","goalsfor":0,"goalsagainst":0,"won":0,"tied":0,"lost":0,"fairplay":0,"points":0,"group":5,"region":"aff"},{"rank":2,"rankwas":1,"team":"FC Ueberstorf III","goalsfor":0,"goalsagainst":0,"won":0,"tied":0,"lost":0,"fairplay":0,"points":0,"group":5,"region":"aff"},{"rank":2,"rankwas":1,"team":"FC Brünisried","goalsfor":0,"goalsagainst":0,"won":0,"tied":0,"lost":0,"fairplay":0,"points":0,"group":5,"region":"aff"},{"rank":2,"rankwas":1,"team":"FC Rechthalten-St.Ursen II","goalsfor":0,"goalsagainst":0,"won":0,"tied":0,"lost":0,"fairplay":0,"points":0,"group":5,"region":"aff"},{"rank":1,"rankwas":1,"team":"FC Kerzers IV","goalsfor":4,"goalsagainst":1,"won":1,"tied":0,"lost":0,"fairplay":0,"points":3,"group":3,"region":"aff"},{"rank":11,"rankwas":1,"team":"FC Cressier II","goalsfor":0,"goalsagainst":1,"won":0,"tied":0,"lost":1,"fairplay":0,"points":0,"group":5,"region":"aff"},{"rank":11,"rankwas":1,"team":"FC Bösingen III","goalsfor":1,"goalsagainst":4,"won":0,"tied":0,"lost":1,"fairplay":0,"points":0,"group":3,"region":"aff"}]}