{"teams":[{"rank":1,"rankwas":1,"team":"FC Seon 1","goalsfor":58,"goalsagainst":11,"won":11,"tied":1,"lost":1,"fairplay":24,"points":34,"group":2,"region":"afv"},{"rank":2,"rankwas":2,"team":"HNK Adria Aarau","goalsfor":34,"goalsagainst":19,"won":8,"tied":3,"lost":1,"fairplay":22,"points":27,"group":2,"region":"afv"},{"rank":5,"rankwas":4,"team":"FC Frick 2a","goalsfor":53,"goalsagainst":22,"won":7,"tied":1,"lost":4,"fairplay":21,"points":22,"group":2,"region":"afv"},{"rank":4,"rankwas":7,"team":"FC Gontenschwil 2","goalsfor":48,"goalsagainst":24,"won":7,"tied":2,"lost":4,"fairplay":7,"points":23,"group":2,"region":"afv"},{"rank":6,"rankwas":5,"team":"FC Villmergen 2a","goalsfor":32,"goalsagainst":24,"won":7,"tied":1,"lost":4,"fairplay":24,"points":22,"group":2,"region":"afv"},{"rank":9,"rankwas":8,"team":"FC Meisterschwanden 1","goalsfor":31,"goalsagainst":29,"won":5,"tied":1,"lost":6,"fairplay":26,"points":16,"group":2,"region":"afv"},{"rank":3,"rankwas":3,"team":"FC Kulm","goalsfor":50,"goalsagainst":29,"won":8,"tied":2,"lost":3,"fairplay":26,"points":26,"group":2,"region":"afv"},{"rank":8,"rankwas":9,"team":"FC Rupperswil 1b","goalsfor":34,"goalsagainst":29,"won":5,"tied":2,"lost":6,"fairplay":28,"points":17,"group":2,"region":"afv"},{"rank":10,"rankwas":10,"team":"FC Lenzburg 3","goalsfor":20,"goalsagainst":39,"won":3,"tied":2,"lost":8,"fairplay":24,"points":11,"group":2,"region":"afv"},{"rank":7,"rankwas":6,"team":"FC Othmarsingen 2","goalsfor":47,"goalsagainst":46,"won":7,"tied":0,"lost":6,"fairplay":24,"points":21,"group":2,"region":"afv"},{"rank":12,"rankwas":12,"team":"FC Rohr 1","goalsfor":14,"goalsagainst":46,"won":3,"tied":1,"lost":8,"fairplay":35,"points":10,"group":2,"region":"afv"},{"rank":14,"rankwas":14,"team":"FC Beinwil am See 2","goalsfor":18,"goalsagainst":49,"won":1,"tied":2,"lost":9,"fairplay":17,"points":5,"group":2,"region":"afv"},{"rank":13,"rankwas":13,"team":"FC Sarmenstorf 2","goalsfor":10,"goalsagainst":49,"won":2,"tied":1,"lost":9,"fairplay":13,"points":7,"group":2,"region":"afv"},{"rank":11,"rankwas":11,"team":"FC Buchs 2","goalsfor":27,"goalsagainst":60,"won":3,"tied":1,"lost":8,"fairplay":31,"points":10,"group":2,"region":"afv"}]}