{"teams":[{"rank":1,"rankwas":1,"team":"US Carouge FC 1","goalsfor":54,"goalsagainst":25,"won":17,"tied":1,"lost":4,"fairplay":0,"points":52,"group":2,"region":"acgf"},{"rank":2,"rankwas":2,"team":"FC Veyrier Sports 2","goalsfor":67,"goalsagainst":29,"won":16,"tied":3,"lost":3,"fairplay":0,"points":51,"group":2,"region":"acgf"},{"rank":4,"rankwas":4,"team":"Meyrin FC 2","goalsfor":68,"goalsagainst":32,"won":11,"tied":2,"lost":9,"fairplay":0,"points":35,"group":2,"region":"acgf"},{"rank":5,"rankwas":5,"team":"FC Grand-Saconnex 1","goalsfor":44,"goalsagainst":39,"won":9,"tied":5,"lost":8,"fairplay":0,"points":32,"group":2,"region":"acgf"},{"rank":8,"rankwas":8,"team":"FC Compesières 1","goalsfor":43,"goalsagainst":43,"won":8,"tied":4,"lost":10,"fairplay":0,"points":28,"group":2,"region":"acgf"},{"rank":9,"rankwas":9,"team":"FC Perly-Certoux 2","goalsfor":46,"goalsagainst":46,"won":8,"tied":3,"lost":11,"fairplay":0,"points":27,"group":2,"region":"acgf"},{"rank":7,"rankwas":7,"team":"CS Italien GE 2","goalsfor":37,"goalsagainst":48,"won":8,"tied":5,"lost":9,"fairplay":0,"points":29,"group":2,"region":"acgf"},{"rank":3,"rankwas":3,"team":"US Meinier 1","goalsfor":55,"goalsagainst":48,"won":12,"tied":2,"lost":8,"fairplay":0,"points":38,"group":2,"region":"acgf"},{"rank":6,"rankwas":6,"team":"FC Puplinge 1","goalsfor":53,"goalsagainst":53,"won":9,"tied":4,"lost":9,"fairplay":0,"points":31,"group":2,"region":"acgf"},{"rank":10,"rankwas":10,"team":"Sporting Futebol Clube 1","goalsfor":50,"goalsagainst":69,"won":8,"tied":2,"lost":12,"fairplay":0,"points":26,"group":2,"region":"acgf"},{"rank":11,"rankwas":11,"team":"CD Cerceda-Genève 1","goalsfor":40,"goalsagainst":78,"won":6,"tied":3,"lost":13,"fairplay":0,"points":21,"group":2,"region":"acgf"},{"rank":12,"rankwas":12,"team":"FC Geneva 1","goalsfor":33,"goalsagainst":80,"won":2,"tied":2,"lost":18,"fairplay":0,"points":8,"group":2,"region":"acgf"}]}