{"teams":[{"rank":1,"rankwas":1,"team":"FC Köniz","goalsfor":20,"goalsagainst":7,"won":7,"tied":2,"lost":0,"fairplay":30,"points":23,"group":1,"region":"fvbj"},{"rank":7,"rankwas":7,"team":"FC Wabern","goalsfor":9,"goalsagainst":10,"won":3,"tied":2,"lost":4,"fairplay":19,"points":11,"group":1,"region":"fvbj"},{"rank":2,"rankwas":2,"team":"FC Spiez","goalsfor":25,"goalsagainst":10,"won":5,"tied":3,"lost":1,"fairplay":22,"points":18,"group":1,"region":"fvbj"},{"rank":4,"rankwas":4,"team":"SC Bümpliz 78","goalsfor":19,"goalsagainst":14,"won":4,"tied":1,"lost":4,"fairplay":18,"points":13,"group":1,"region":"fvbj"},{"rank":8,"rankwas":8,"team":"FC Dürrenast","goalsfor":11,"goalsagainst":15,"won":3,"tied":2,"lost":4,"fairplay":21,"points":11,"group":1,"region":"fvbj"},{"rank":11,"rankwas":11,"team":"FC Interlaken","goalsfor":12,"goalsagainst":16,"won":2,"tied":3,"lost":4,"fairplay":20,"points":9,"group":1,"region":"fvbj"},{"rank":9,"rankwas":9,"team":"FC Breitenrain","goalsfor":12,"goalsagainst":16,"won":3,"tied":2,"lost":4,"fairplay":46,"points":11,"group":1,"region":"fvbj"},{"rank":3,"rankwas":3,"team":"FC Ostermundigen","goalsfor":19,"goalsagainst":17,"won":5,"tied":1,"lost":3,"fairplay":21,"points":16,"group":1,"region":"fvbj"},{"rank":10,"rankwas":10,"team":"FC Wyler","goalsfor":18,"goalsagainst":19,"won":3,"tied":1,"lost":5,"fairplay":29,"points":10,"group":1,"region":"fvbj"},{"rank":5,"rankwas":5,"team":"AS Italiana","goalsfor":19,"goalsagainst":21,"won":4,"tied":1,"lost":4,"fairplay":23,"points":13,"group":1,"region":"fvbj"},{"rank":12,"rankwas":12,"team":"FC Rothorn","goalsfor":8,"goalsagainst":21,"won":2,"tied":0,"lost":7,"fairplay":29,"points":6,"group":1,"region":"fvbj"},{"rank":6,"rankwas":6,"team":"FC Kirchberg","goalsfor":15,"goalsagainst":21,"won":4,"tied":0,"lost":5,"fairplay":9,"points":12,"group":1,"region":"fvbj"}]}