{"teams":[{"rank":1,"rankwas":1,"team":"FC Einsiedeln 2","goalsfor":3,"goalsagainst":0,"won":1,"tied":0,"lost":0,"fairplay":0,"points":3,"group":1,"region":"fvrz","evolution":[1]},{"rank":1,"rankwas":1,"team":"FC Freienbach 2","goalsfor":3,"goalsagainst":0,"won":1,"tied":0,"lost":0,"fairplay":0,"points":3,"group":1,"region":"fvrz","evolution":[1]},{"rank":3,"rankwas":3,"team":"FC Richterswil 1","goalsfor":1,"goalsagainst":0,"won":1,"tied":0,"lost":0,"fairplay":0,"points":3,"group":1,"region":"fvrz","evolution":[1]},{"rank":4,"rankwas":4,"team":"FC Lachen/Altendorf 3","goalsfor":2,"goalsagainst":2,"won":0,"tied":1,"lost":0,"fairplay":0,"points":1,"group":1,"region":"fvrz","evolution":[1]},{"rank":4,"rankwas":4,"team":"FC Feusisberg-Schindellegi 1","goalsfor":2,"goalsagainst":2,"won":0,"tied":1,"lost":0,"fairplay":0,"points":1,"group":1,"region":"fvrz","evolution":[1]},{"rank":6,"rankwas":6,"team":"SC Siebnen 2","goalsfor":1,"goalsagainst":1,"won":0,"tied":1,"lost":0,"fairplay":0,"points":1,"group":1,"region":"fvrz","evolution":[1]},{"rank":6,"rankwas":6,"team":"FC Tuggen 2","goalsfor":1,"goalsagainst":1,"won":0,"tied":1,"lost":0,"fairplay":0,"points":1,"group":1,"region":"fvrz","evolution":[1]},{"rank":8,"rankwas":8,"team":"FC Horgen 2","goalsfor":0,"goalsagainst":0,"won":0,"tied":0,"lost":0,"fairplay":0,"points":0,"group":1,"region":"fvrz","evolution":[1]},{"rank":9,"rankwas":9,"team":"FC Wädenswil 3","goalsfor":0,"goalsagainst":1,"won":0,"tied":0,"lost":1,"fairplay":0,"points":0,"group":1,"region":"fvrz","evolution":[1]},{"rank":10,"rankwas":10,"team":"FC Wollerau 2","goalsfor":0,"goalsagainst":3,"won":0,"tied":0,"lost":1,"fairplay":0,"points":0,"group":1,"region":"fvrz","evolution":[1]},{"rank":10,"rankwas":10,"team":"FC Buttikon 2","goalsfor":0,"goalsagainst":3,"won":0,"tied":0,"lost":1,"fairplay":0,"points":0,"group":1,"region":"fvrz","evolution":[1]}]}