{"rankings":[{"groupNumber":1,"scorers":[{"scorer":"Frederik Ellegaard","goals":5,"team":"US Meinier 1"},{"scorer":"Elias Pasche","goals":2,"team":"Lancy FC 2"},{"scorer":"Jean Lappert","goals":2,"team":"FC Collex-Bossy 2"},{"scorer":"Sébastien Lachenal","goals":2,"team":"Lancy FC 2"},{"scorer":"Johann Lazzarelli","goals":2,"team":"US Meinier 1"},{"scorer":"Irnes Catic","goals":2,"team":"FC Rapid Jonction Bosna 1"},{"scorer":"Dylan Prezioso","goals":2,"team":"US Genève-Poste FC 1"},{"scorer":"Adam Khettabi","goals":2,"team":"FC Puplinge 1"},{"scorer":"Quentin Van der Schüren","goals":2,"team":"Signal FC Bernex-Confignon 2"},{"scorer":"Marco Da Silva","goals":2,"team":"US Meinier 1"}]},{"groupNumber":2,"scorers":[{"scorer":"Iheb Ben Farhat","goals":3,"team":"Etoile Carouge FC 2"},{"scorer":"Davide Santos","goals":2,"team":"CS Interstar 2"}]}],"lastUpdate":"7/9/2017 @ 9h00","lastUpdateForSiteMap":"2017-09-07"}