{"teams":[{"rank":3,"rankwas":3,"team":"Team Haut-Lac (5054) II","goalsfor":4,"goalsagainst":0,"won":1,"tied":1,"lost":0,"fairplay":2,"points":4,"group":3,"region":"aff"},{"rank":1,"rankwas":1,"team":"FC Givisiez Ia","goalsfor":13,"goalsagainst":1,"won":2,"tied":0,"lost":0,"fairplay":2,"points":6,"group":3,"region":"aff"},{"rank":2,"rankwas":2,"team":"FC Avenches II","goalsfor":4,"goalsagainst":2,"won":2,"tied":0,"lost":0,"fairplay":3,"points":6,"group":3,"region":"aff"},{"rank":4,"rankwas":4,"team":"FC Léchelles I","goalsfor":3,"goalsagainst":2,"won":1,"tied":1,"lost":0,"fairplay":3,"points":4,"group":3,"region":"aff"},{"rank":5,"rankwas":5,"team":"FC Domdidier II","goalsfor":3,"goalsagainst":2,"won":1,"tied":1,"lost":0,"fairplay":4,"points":4,"group":3,"region":"aff"},{"rank":9,"rankwas":9,"team":"FC Montagny I","goalsfor":2,"goalsagainst":3,"won":0,"tied":1,"lost":1,"fairplay":1,"points":1,"group":3,"region":"aff"},{"rank":10,"rankwas":11,"team":"FC Montbrelloz I","goalsfor":2,"goalsagainst":4,"won":0,"tied":0,"lost":2,"fairplay":2,"points":0,"group":3,"region":"aff"},{"rank":8,"rankwas":8,"team":"FC Ressudens I","goalsfor":3,"goalsagainst":4,"won":1,"tied":0,"lost":1,"fairplay":4,"points":3,"group":3,"region":"aff"},{"rank":6,"rankwas":6,"team":"FC Corminboeuf II","goalsfor":7,"goalsagainst":5,"won":1,"tied":0,"lost":1,"fairplay":2,"points":3,"group":3,"region":"aff"},{"rank":12,"rankwas":12,"team":"ES Belfaux II","goalsfor":3,"goalsagainst":5,"won":0,"tied":0,"lost":2,"fairplay":9,"points":0,"group":3,"region":"aff"},{"rank":7,"rankwas":7,"team":"FC Saint-Aubin/Vallon IIa","goalsfor":3,"goalsagainst":9,"won":1,"tied":0,"lost":1,"fairplay":3,"points":3,"group":3,"region":"aff"},{"rank":11,"rankwas":10,"team":"FC Billens Ib","goalsfor":0,"goalsagainst":10,"won":0,"tied":0,"lost":2,"fairplay":2,"points":0,"group":3,"region":"aff"}]}