{"rankings":[{"groupNumber":1,"scorers":[{"scorer":"Aline Neuhaus","goals":6,"team":"FC Plaffeien"},{"scorer":"Nathalie Maillard","goals":2,"team":"FC Sarine-Ouest"},{"scorer":"Nila Lagger","goals":2,"team":"FC Cugy/Montet"},{"scorer":"Caroline Gangl","goals":2,"team":"FC Alterswil"},{"scorer":"Svenja Fasel","goals":2,"team":"FC Courgevaux II"},{"scorer":"Mylène Hermann","goals":2,"team":"FCFF Villars-sur-Glâne"},{"scorer":"Sumeja Salihi","goals":2,"team":"FC Bas-Gibloux"},{"scorer":"Véronique Piller","goals":1,"team":"FC Plaffeien"},{"scorer":"Aurelie Macherel","goals":1,"team":"FC Bas-Gibloux"},{"scorer":"Melissa Macheret","goals":1,"team":"FC Bas-Gibloux"},{"scorer":"Tanja Feuz","goals":1,"team":"FC Alterswil"},{"scorer":"Olivia Pradervand","goals":1,"team":"FC Cugy/Montet"},{"scorer":"Josiane Neff","goals":1,"team":"FC Cugy/Montet"},{"scorer":"Catarina Da Silva","goals":1,"team":"FCFF Villars-sur-Glâne"},{"scorer":"Fabienne Käser","goals":1,"team":"FC Plaffeien"},{"scorer":"Cassandre Anthamatten","goals":1,"team":"FCFF Villars-sur-Glâne"},{"scorer":"Sandrine Stucky","goals":1,"team":"FC Sarine-Ouest"},{"scorer":"Corinne Aebischer","goals":1,"team":"FC Alterswil"},{"scorer":"Tania Alexandra Santos","goals":1,"team":"FC Sarine-Ouest"},{"scorer":"Marie Therese Voirol","goals":1,"team":"FC Bas-Gibloux"},{"scorer":"Anastasia Kocoski","goals":1,"team":"FC Murten"}]}],"lastUpdate":"5/9/2016 @ 17h00"}