{"teams":[{"rank":1,"rankwas":1,"team":"FC Langnau","goalsfor":17,"goalsagainst":3,"won":4,"tied":0,"lost":0,"fairplay":5,"points":12,"group":4,"region":"fvbj","evolution":[1]},{"rank":2,"rankwas":2,"team":"FC Roggwil","goalsfor":11,"goalsagainst":6,"won":3,"tied":1,"lost":0,"fairplay":7,"points":10,"group":4,"region":"fvbj","evolution":[2]},{"rank":3,"rankwas":3,"team":"SV Sumiswald","goalsfor":6,"goalsagainst":5,"won":2,"tied":1,"lost":1,"fairplay":9,"points":7,"group":4,"region":"fvbj","evolution":[3]},{"rank":4,"rankwas":4,"team":"FC Langenthal","goalsfor":11,"goalsagainst":6,"won":2,"tied":1,"lost":1,"fairplay":17,"points":7,"group":4,"region":"fvbj","evolution":[4]},{"rank":5,"rankwas":5,"team":"KF Shqiponja","goalsfor":11,"goalsagainst":8,"won":2,"tied":0,"lost":1,"fairplay":6,"points":6,"group":4,"region":"fvbj","evolution":[5]},{"rank":6,"rankwas":6,"team":"FC Zollbrück","goalsfor":13,"goalsagainst":6,"won":2,"tied":0,"lost":2,"fairplay":3,"points":6,"group":4,"region":"fvbj","evolution":[6]},{"rank":7,"rankwas":7,"team":"FC Herzogenbuchsee","goalsfor":6,"goalsagainst":4,"won":1,"tied":3,"lost":0,"fairplay":3,"points":6,"group":4,"region":"fvbj","evolution":[7]},{"rank":8,"rankwas":8,"team":"SC Burgdorf","goalsfor":6,"goalsagainst":6,"won":1,"tied":2,"lost":1,"fairplay":8,"points":5,"group":4,"region":"fvbj","evolution":[8]},{"rank":9,"rankwas":9,"team":"FC Blau Weiss Oberburg","goalsfor":4,"goalsagainst":17,"won":1,"tied":0,"lost":3,"fairplay":9,"points":3,"group":4,"region":"fvbj","evolution":[9]},{"rank":10,"rankwas":10,"team":"FC Kirchberg","goalsfor":5,"goalsagainst":11,"won":0,"tied":1,"lost":3,"fairplay":11,"points":1,"group":4,"region":"fvbj","evolution":[10]},{"rank":11,"rankwas":11,"team":"FC Utzenstorf","goalsfor":5,"goalsagainst":12,"won":0,"tied":1,"lost":3,"fairplay":11,"points":1,"group":4,"region":"fvbj","evolution":[11]},{"rank":12,"rankwas":12,"team":"Koppiger SV","goalsfor":3,"goalsagainst":14,"won":0,"tied":0,"lost":3,"fairplay":5,"points":0,"group":4,"region":"fvbj","evolution":[12]}]}