{"teams":[{"rank":1,"rankwas":1,"team":"FC Köniz","goalsfor":25,"goalsagainst":7,"won":8,"tied":2,"lost":0,"fairplay":30,"points":26,"group":1,"region":"fvbj","evolution":[1]},{"rank":2,"rankwas":2,"team":"FC Spiez","goalsfor":29,"goalsagainst":12,"won":6,"tied":3,"lost":1,"fairplay":22,"points":21,"group":1,"region":"fvbj","evolution":[2]},{"rank":3,"rankwas":3,"team":"FC Ostermundigen","goalsfor":20,"goalsagainst":17,"won":6,"tied":1,"lost":3,"fairplay":21,"points":19,"group":1,"region":"fvbj","evolution":[10]},{"rank":4,"rankwas":4,"team":"SC Bümpliz 78","goalsfor":21,"goalsagainst":15,"won":5,"tied":1,"lost":4,"fairplay":18,"points":16,"group":1,"region":"fvbj","evolution":[11]},{"rank":5,"rankwas":5,"team":"FC Kirchberg","goalsfor":18,"goalsagainst":22,"won":5,"tied":0,"lost":5,"fairplay":9,"points":15,"group":1,"region":"fvbj","evolution":[5]},{"rank":6,"rankwas":6,"team":"FC Breitenrain","goalsfor":15,"goalsagainst":18,"won":4,"tied":2,"lost":4,"fairplay":46,"points":14,"group":1,"region":"fvbj","evolution":[4]},{"rank":7,"rankwas":7,"team":"AS Italiana","goalsfor":21,"goalsagainst":24,"won":4,"tied":1,"lost":5,"fairplay":23,"points":13,"group":1,"region":"fvbj","evolution":[3]},{"rank":8,"rankwas":8,"team":"FC Wabern","goalsfor":9,"goalsagainst":15,"won":3,"tied":2,"lost":5,"fairplay":19,"points":11,"group":1,"region":"fvbj","evolution":[6]},{"rank":9,"rankwas":9,"team":"FC Dürrenast","goalsfor":12,"goalsagainst":17,"won":3,"tied":2,"lost":5,"fairplay":21,"points":11,"group":1,"region":"fvbj","evolution":[8]},{"rank":10,"rankwas":10,"team":"FC Wyler","goalsfor":18,"goalsagainst":20,"won":3,"tied":1,"lost":6,"fairplay":29,"points":10,"group":1,"region":"fvbj","evolution":[12]},{"rank":11,"rankwas":11,"team":"FC Interlaken","goalsfor":13,"goalsagainst":19,"won":2,"tied":3,"lost":5,"fairplay":20,"points":9,"group":1,"region":"fvbj","evolution":[9]},{"rank":12,"rankwas":12,"team":"FC Rothorn","goalsfor":10,"goalsagainst":25,"won":2,"tied":0,"lost":8,"fairplay":29,"points":6,"group":1,"region":"fvbj","evolution":[7]}]}