{"top5scorers":[{"scorer":"Simon Affentranger","goals":6,"team":"SC Fulenbach"},{"scorer":"Samuel Zayas","goals":5,"team":"FC Grenchen 15"},{"scorer":"Cyrill Sonderegger","goals":4,"team":"FC Lommiswil"},{"scorer":"Tim Büttiker","goals":3,"team":"FC Härkingen"},{"scorer":"Kliment Nastoski","goals":2,"team":"FC Grenchen 15"},{"scorer":"csc","goals":2,"team":"FC Iliria"},{"scorer":"Bojan Djuric","goals":2,"team":"FC Oensingen"},{"scorer":"Dominik Schaller","goals":1,"team":"FC Härkingen"},{"scorer":"Alessandro Fragale","goals":1,"team":"FC Bellach"},{"scorer":"Andreas Ackermann","goals":1,"team":"FC Mümliswil"},{"scorer":"Wasili Bielmann","goals":1,"team":"FC Bellach"},{"scorer":"Michel Syfrig","goals":1,"team":"SC Blustavia"},{"scorer":"Arben Alimusaj","goals":1,"team":"FC Grenchen 15"},{"scorer":"Borislav Jankovic","goals":1,"team":"FC Oensingen"},{"scorer":"Dasnim Sulejmani","goals":1,"team":"FC Iliria"},{"scorer":"Egzon Mustafi","goals":1,"team":"FC Iliria"},{"scorer":"Ramon Spring","goals":1,"team":"SC Blustavia"},{"scorer":"Raphael Büttiker","goals":1,"team":"FC Härkingen"},{"scorer":"Avdi Haljimi","goals":1,"team":"FC Iliria"},{"scorer":"Lucien Baumgartner","goals":1,"team":"FC Trimbach"}]}