{"top5scorers":[{"scorer":"Yanick Oumaray","goals":4,"team":"FC Härkingen"},{"scorer":"Samuel Zayas","goals":3,"team":"FC Grenchen 15"},{"scorer":"Péter Csima","goals":2,"team":"FC Grenchen 15"},{"scorer":"Bojan Djuric","goals":2,"team":"FC Oensingen"},{"scorer":"csc","goals":2,"team":"FC Iliria"},{"scorer":"Aaron Sperisen","goals":2,"team":"FC Subingen"},{"scorer":"Andreas Ackermann","goals":1,"team":"FC Mümliswil"},{"scorer":"Dzevahir Ramani","goals":1,"team":"FC Grenchen 15"},{"scorer":"Mario Stecher","goals":1,"team":"FC Härkingen"},{"scorer":"Dominik Schaller","goals":1,"team":"FC Härkingen"},{"scorer":"Fabian Wyss","goals":1,"team":"SC Fulenbach"},{"scorer":"David Steiner","goals":1,"team":"FC Bellach"},{"scorer":"Egzon Mustafi","goals":1,"team":"FC Iliria"},{"scorer":"Michel Syfrig","goals":1,"team":"SC Blustavia"},{"scorer":"Ramon Spring","goals":1,"team":"SC Blustavia"},{"scorer":"Christian Oetterli","goals":1,"team":"SC Blustavia"},{"scorer":"Lucien Baumgartner","goals":1,"team":"FC Trimbach"},{"scorer":"Sandro Schalt","goals":1,"team":"FC Trimbach"},{"scorer":"Borislav Jankovic","goals":1,"team":"FC Oensingen"},{"scorer":"Dasnim Sulejmani","goals":1,"team":"FC Iliria"}]}